rlymbb/__init__.py
rlymbb/rlymbb.py
rlymbb-4.1.0.dist-info/licenses/LICENSE
rlymbb-4.1.0.dist-info/METADATA
rlymbb-4.1.0.dist-info/WHEEL
rlymbb-4.1.0.dist-info/top_level.txt
rlymbb-4.1.0.dist-info/RECORD
