Metadata-Version: 2.4
Name: rlymbb
Version: 4.1.0
Summary: reqwest
Author-email: rlybb <sordealpro@gmail.com>
Project-URL: Homepage, https://github.com/rlyv/
Classifier: Programming Language :: Python :: 3
Classifier: License :: OSI Approved :: MIT License
Classifier: Operating System :: OS Independent
Requires-Python: >=3.6
License-File: LICENSE
Requires-Dist: requests>=2.25.0
Dynamic: license-file
